Metadata-Version: 1.1
Name: unittestingdf
Version: 0.0.1
Summary: A very basic calculator
Home-page: UNKNOWN
Author: Jeyasuriya
Author-email: suriyajeyasuriya123@gmail.com
License: MIT
Keywords: testingDataFrame
Platform: UNKNOWN
Classifier: Development Status :: 5 - Production/Stable
Classifier: Intended Audience :: Education
Classifier: Operating System :: Microsoft :: Windows :: Windows 10
Classifier: License :: OSI Approved :: MIT License
Classifier: Programming Language :: Python :: 3
